seedhelper/libstructureshelper.so
seedhelper/__init__.py
seedhelper/structures.py
seedhelper-0.1.4.dist-info/RECORD
seedhelper-0.1.4.dist-info/LICENSE
seedhelper-0.1.4.dist-info/WHEEL
seedhelper-0.1.4.dist-info/top_level.txt
seedhelper-0.1.4.dist-info/METADATA
