Metadata-Version: 2.1
Name: seedhelper
Version: 0.1.4
Summary: A python library that help to find specific Minecraft structures or biomes for a given seed.
Author: Louis Pagnier
License: MIT
Keywords: minecraft,seed,biome,structure,elytra
Classifier: License :: OSI Approved :: MIT License
Classifier: Programming Language :: Python :: 3
Requires-Python: >=3.10
License-File: LICENSE
